{
  "id": "aba26c00-c784-44c4-a9da-f2cc59b6ea32",
  "domain_name": "SausageMaking",
  "directory": "sausage_making",
  "version": "2026.04.10.1",
  "vision": "Manages sausage production from meat grinding to cured links",
  "path": "nursery/sausage_making/sausage_making.bluebook",
  "line_count": 112,
  "aggregate_count": 3,
  "command_count": 7,
  "policy_count": 1,
  "event_count": 7,
  "lifecycle_count": 3,
  "aggregate_names": [
    "MeatBatch",
    "StuffingRun",
    "CuringChamber"
  ],
  "sector": "general",
  "tags": [
    "general"
  ],
  "created_at": "2026-04-10T01:17:28-07:00",
  "updated_at": "2026-04-10T01:18:14-07:00"
}